ldap2jira/__init__.py
ldap2jira/ldap_lookup.py
ldap2jira/map.py
ldap2jira/version.py
tests/__init__.py
tests/test_ldap2jira.py
tests/test_map.csv
tests/test_map.json
ldap2jira-1.2.4.dist-info/LICENSE
ldap2jira-1.2.4.dist-info/METADATA
ldap2jira-1.2.4.dist-info/WHEEL
ldap2jira-1.2.4.dist-info/top_level.txt
ldap2jira-1.2.4.dist-info/RECORD
