Metadata-Version: 2.1
Name: ldap2jira
Version: 1.2.4
Summary: Set of utilities for finding jira accounts with LDAP check and optional file map
Home-page: https://github.com/RedHat-Eng-PGM/python-ldap2jira
Author: RH PLM
Author-email: pp-dev-list@redhat.com
License: MIT
Project-URL: Bug Tracker, https://github.com/RedHat-Eng-PGM/python-ldap2jira/issues
Classifier: Programming Language :: Python :: 3
Classifier: Programming Language :: Python :: 3.7
Classifier: Programming Language :: Python :: 3.8
Classifier: Programming Language :: Python :: 3.9
Classifier: License :: OSI Approved :: MIT License
Requires-Python: >=3.7
License-File: LICENSE
Requires-Dist: jira
Requires-Dist: python-ldap
